keyring_proxy_env/__init__.py
keyring_proxy_env/_version.py
keyring_proxy_env/py.typed
keyring_proxy_env-0.2.12.6.dist-info/METADATA
keyring_proxy_env-0.2.12.6.dist-info/WHEEL
keyring_proxy_env-0.2.12.6.dist-info/entry_points.txt
keyring_proxy_env-0.2.12.6.dist-info/RECORD
